CHANGES.rst
COPYING
MANIFEST.in
README.rst
setup.cfg
setup.py
tox-bench.ini
tox.ini
update_c.sh
datrie_extended.egg-info/PKG-INFO
datrie_extended.egg-info/SOURCES.txt
datrie_extended.egg-info/dependency_links.txt
datrie_extended.egg-info/top_level.txt
libdatrie/datrie/alpha-map-private.h
libdatrie/datrie/alpha-map.c
libdatrie/datrie/alpha-map.h
libdatrie/datrie/darray.c
libdatrie/datrie/darray.h
libdatrie/datrie/dstring-private.h
libdatrie/datrie/dstring.c
libdatrie/datrie/dstring.h
libdatrie/datrie/fileutils.c
libdatrie/datrie/fileutils.h
libdatrie/datrie/tail.c
libdatrie/datrie/tail.h
libdatrie/datrie/trie-private.h
libdatrie/datrie/trie-string.c
libdatrie/datrie/trie-string.h
libdatrie/datrie/trie.c
libdatrie/datrie/trie.h
libdatrie/datrie/triedefs.h
libdatrie/datrie/typedefs.h
libdatrie/tests/test_file.c
libdatrie/tests/test_iterator.c
libdatrie/tests/test_nonalpha.c
libdatrie/tests/test_null_trie.c
libdatrie/tests/test_store-retrieve.c
libdatrie/tests/test_walk.c
libdatrie/tests/utils.c
libdatrie/tests/utils.h
libdatrie/tools/trietool.c
src/cdatrie.c
src/cdatrie.pxd
src/datrie.c
src/datrie.pyx
src/stdio_ext.c
src/stdio_ext.pxd
tests/__init__.py
tests/test_iteration.py
tests/test_random.py
tests/test_state.py
tests/test_trie.py